nsinfo/__init__.py
nsinfo/structures.py
nsinfo-0.2.1.dist-info/METADATA
nsinfo-0.2.1.dist-info/WHEEL
nsinfo-0.2.1.dist-info/top_level.txt
nsinfo-0.2.1.dist-info/RECORD
