Metadata-Version: 2.1
Name: nsinfo
Version: 0.2.1
Summary: Une bibliothèque Python qui vise à implémenter ce qu'on utilise en NSI (Piles, Files, Graphes, etc.)
Home-page: https://github.com/TataneSan/nsi
Author: TataneSan
Author-email: admin@tatanesan.fr
Classifier: Programming Language :: Python :: 3
Classifier: License :: OSI Approved :: MIT License
Classifier: Operating System :: OS Independent
Requires-Python: >=3.6
